vaxm/__init__.py
vaxm/vax.py
vaxm-0.1.4.dist-info/LICENSE.txt
vaxm-0.1.4.dist-info/METADATA
vaxm-0.1.4.dist-info/WHEEL
vaxm-0.1.4.dist-info/top_level.txt
vaxm-0.1.4.dist-info/RECORD
