Metadata-Version: 2.2
Name: vaxm
Version: 0.1.4
Summary: A Python package to the VAX method, supporting multivariate data explanation by Jumping Emerging Patterns.
Home-page: https://gitlab.com/popolinneto/vaxm
Author: Mario Popolin Neto
License: Creative Commons Attribution-NonCommercial-ShareAlike 4.0 International
Classifier: License :: Free for non-commercial use
Classifier: Operating System :: OS Independent
Classifier: Programming Language :: Python :: 3
Requires-Python: >=3.6
License-File: LICENSE.txt
Requires-Dist: lrmatrix>=0.1.5
Dynamic: author
Dynamic: classifier
Dynamic: description
Dynamic: description-content-type
Dynamic: home-page
Dynamic: license
Dynamic: requires-dist
Dynamic: requires-python
Dynamic: summary
